{
  "name": "Secretary of Transportation",
  "slug": "secretary-of-transportation",
  "tags": [
    "politics",
    "us-politics",
    "governance",
    "infrastructure"
  ],
  "chapters": [
    {
      "name": "Sean Duffy",
      "slug": "sean-duffy",
      "topics": [
        "What is Sean Duffy's background before becoming Transportation Secretary?",
        "What was Sean Duffy's record in Congress?",
        "What are Sean Duffy's positions on infrastructure and transportation?",
        "What controversies or concerns surround Sean Duffy's appointment?",
        "How did Sean Duffy's confirmation process unfold?"
      ],
      "tags": [
        "politics",
        "us-politics",
        "governance",
        "infrastructure"
      ]
    },
    {
      "name": "Previous Secretary",
      "slug": "previous-secretary",
      "topics": [
        "Who was the previous (Biden) Transportation Secretary and what was their tenure like?",
        "How does Sean Duffy's approach differ from his predecessor?"
      ],
      "tags": [
        "politics",
        "us-politics",
        "governance",
        "infrastructure"
      ]
    }
  ]
}
