[
  {
    "slug": "one-mind-many-machines-how-solo-builders-now-outpace-legacy-platforms",
    "name": "One Mind, Many Machines: How Solo Builders Now Outpace Legacy Platforms",
    "description": null,
    "chapterCount": 20,
    "tags": []
  },
  {
    "slug": "philosophy-of-knowledge",
    "name": "Philosophy of Knowledge",
    "description": null,
    "chapterCount": 3,
    "tags": []
  },
  {
    "slug": "recursive-knowledge-authorship",
    "name": "Recursive Knowledge Authorship",
    "description": null,
    "chapterCount": 3,
    "tags": []
  },
  {
    "slug": "the-ethics-of-information",
    "name": "The Ethics of Information",
    "description": null,
    "chapterCount": 3,
    "tags": []
  },
  {
    "slug": "what-is-quarex",
    "name": "What Is Quarex?",
    "description": null,
    "chapterCount": 4,
    "tags": []
  },
  {
    "slug": "what-is-the-quarex-as-used-in-the-truthangel",
    "name": "What Is the quarex as used in the TruthAngel?",
    "description": null,
    "chapterCount": 3,
    "tags": []
  }
]